LICENSE
MANIFEST.in
README.md
setup.cfg
setup.py
oembed/__init__.py
oembed/apps.py
oembed/caching.py
oembed/discoverers.py
oembed/jinja.py
oembed/models.py
oembed/parse.py
oembed/response.py
oembed/settings.py
oembed/urls.py
oembed/utils.py
oembed/views.py
oembed/fixtures/providers.json
oembed/templates/oembed/placeholder.inc.html
oembed/templatetags/__init__.py
oembed/templatetags/oembed.py
podiant_oembed.egg-info/PKG-INFO
podiant_oembed.egg-info/SOURCES.txt
podiant_oembed.egg-info/dependency_links.txt
podiant_oembed.egg-info/not-zip-safe
podiant_oembed.egg-info/requires.txt
podiant_oembed.egg-info/top_level.txt