Metadata-Version: 2.1
Name: podiant-oembed
Version: 2.0.0
Summary: A simple, flexible oEmbed provider and consumer
Home-page: https://git.steadman.io/podiant/oembed
Author: Mark Steadman
Author-email: mark@podiant.co
License: MIT
Keywords: podiant-oembed
Platform: UNKNOWN
Classifier: Development Status :: 3 - Alpha
Classifier: Framework :: Django :: 1.11
Classifier: Intended Audience :: Developers
Classifier: License :: OSI Approved :: BSD License
Classifier: Natural Language :: English
Classifier: Programming Language :: Python :: 3
Classifier: Programming Language :: Python :: 3.4
Classifier: Programming Language :: Python :: 3.5
Classifier: Programming Language :: Python :: 3.6
